all_math_ops/__init__.py
all_math_ops/__version__.py
all_math_ops/addition_module.py
all_math_ops/division_module.py
all_math_ops/multiplication_module.py
all_math_ops/subtraction_module.py
all_math_ops-1.0.dist-info/METADATA
all_math_ops-1.0.dist-info/WHEEL
all_math_ops-1.0.dist-info/top_level.txt
all_math_ops-1.0.dist-info/RECORD
