Metadata-Version: 2.2
Name: all_math_ops
Version: 1.0
Summary: A simple package for matho perations
Author: Raghu
Author-email: raghu@abc.com
Classifier: Programming Language :: Python :: 3
Classifier: License :: OSI Approved :: MIT License
Classifier: Operating System :: OS Independent
Requires-Python: >=3.8
Dynamic: author
Dynamic: author-email
Dynamic: classifier
Dynamic: requires-python
Dynamic: summary
